Verilog/fsm_wearable.v
module fsm_wearable (
    input wire clk,
    input wire rst_n,
    input wire [5:0] sensor_inputs,
    output reg [5:0] actuator_outputs,
    output reg [1:0] state_code
);

    // State Encoding
    localparam IDLE           = 2'b00;
    localparam LIGHT_DEHY     = 2'b01;
    localparam SEVERE_DEHY    = 2'b10;
    localparam ACTIVITY_ALERT = 2'b11;

    // Internal Signals
    reg [1:0] current_state, next_state;
    reg [5:0] sync_buffer1;
    reg [5:0] sync_buffer2; // Synced inputs

    // 2-Stage Synchronizer
    always @(posedge clk or negedge rst_n) begin
        if (!rst_n) begin
            sync_buffer1 <= 6'b0;
            sync_buffer2 <= 6'b0;
        end else begin
            sync_buffer1 <= sensor_inputs;
            sync_buffer2 <= sync_buffer1;
        end
    end

    // Priority Detection Logic
    wire p1_detect, p2_detect, p3_detect;
    wire [2:0] active_sensor_count;

    // P1: S5=1 AND any of (S1 OR S2 OR S3 OR S4)=1
    assign p1_detect = sync_buffer2[4] && (sync_buffer2[0] || sync_buffer2[1] || sync_buffer2[2] || sync_buffer2[3]);

    // P2: S6=1
    assign p2_detect = sync_buffer2[5];

    // P3: sum(S1..S5) >= 2
    // We need to count bits set in S1-S5 (indices 0-4)
    assign active_sensor_count = sync_buffer2[0] + sync_buffer2[1] + sync_buffer2[2] + sync_buffer2[3] + sync_buffer2[4];
    assign p3_detect = (active_sensor_count >= 3'd2);

    // Next State Logic (Combinational)
    always @(*) begin
        // Strict priority hierarchy: P1 > P2 > P3 > P4
        if (p1_detect)
            next_state = SEVERE_DEHY;
        else if (p2_detect)
            next_state = ACTIVITY_ALERT;
        else if (p3_detect)
            next_state = LIGHT_DEHY;
        else
            next_state = IDLE;
    end

    // State Register Update
    always @(posedge clk or negedge rst_n) begin
        if (!rst_n)
            current_state <= IDLE;
        else
            current_state <= next_state;
    end

    // Output Logic (Moore)
    always @(*) begin
        state_code = current_state;
        case (current_state)
            IDLE:           actuator_outputs = 6'b000000;
            LIGHT_DEHY:     actuator_outputs = 6'b101100; // A1, A3, A4 ON
            SEVERE_DEHY:    actuator_outputs = 6'b111111; // All ON
            ACTIVITY_ALERT: actuator_outputs = 6'b101110; // A1, A3, A4, A5 ON
            default:        actuator_outputs = 6'b000000;
        endcase
    end

endmodule

Verilog/tb_fsm_wearable.v
`timescale 1ns/1ps

module tb_fsm_wearable;

    //==========================================================
    // TESTBENCH SIGNALS
    //==========================================================
    reg clk;
    reg reset_n;
    reg [5:0] S_input;
    wire [5:0] A_output;
    wire [1:0] state_out;
    
    // Test tracking
    integer test_count;
    integer pass_count;
    integer fail_count;
    reg [80:1] state_name;
    
    //==========================================================
    // INSTANTIATE DUT (Device Under Test)
    //==========================================================
    fsm_wearable uut (
        .clk(clk),
        .rst_n(reset_n),
        .sensor_inputs(S_input),
        .actuator_outputs(A_output),
        .state_code(state_out)
    );

     //==========================================================
    // VCD WAVEFORM DUMP
    //==========================================================
    initial begin
        // Create VCD file for waveform viewing
        $dumpfile("fsm_waveform.vcd");
        $dumpvars(0, tb_fsm_wearable);  // Level 0 = dump all signals
    end
    
    //==========================================================
    // CLOCK GENERATION (100 MHz = 10ns period)
    //==========================================================
    initial begin
        clk = 0;
        forever #5 clk = ~clk;  // Toggle every 5ns
    end
    
    //==========================================================
    // TASK: CHECK OUTPUT
    //==========================================================
    task check_output;
        input [5:0] expected;
        input [8*50:1] test_name;
        begin
            test_count = test_count + 1;
            #50;  // Wait for output to stabilize (5 clock cycles)
            
            if (A_output === expected) begin
                $display("[PASS] Test %0d: %s", test_count, test_name);
                $display("       Input: S=%b, Output: A=%b (Expected: %b)", 
                         S_input, A_output, expected);
                pass_count = pass_count + 1;
            end else begin
                $display("[FAIL] Test %0d: %s", test_count, test_name);
                $display("       Input: S=%b, Output: A=%b (Expected: %b)", 
                         S_input, A_output, expected);
                fail_count = fail_count + 1;
            end
            $display("-----------------------------------------------");
        end
    endtask
    
    //==========================================================
    // TASK: APPLY RESET
    //==========================================================
    task apply_reset;
        begin
            $display("\n[INFO] Applying reset...");
            reset_n = 0;
            S_input = 6'b000000;
            #30;
            reset_n = 1;
            #20;
            $display("[INFO] Reset complete. Starting tests...\n");
            $display("===============================================");
        end
    endtask
    
    //==========================================================
    // MAIN TEST SEQUENCE
    //==========================================================
    initial begin
        // Initialize counters
        test_count = 0;
        pass_count = 0;
        fail_count = 0;
        
        // Initialize signals
        clk = 0;
        reset_n = 1;
        S_input = 6'b000000;
        
        $display("\n");
        $display("***********************************************");
        $display("*  FSM WEARABLE DEHYDRATION DETECTION TEST   *");
        $display("***********************************************");
        
        // Apply reset
        apply_reset();
        
        //==========================================================
        // CATEGORY 1: IDLE STATE TESTS (P4 Priority)
        //==========================================================
        $display("\n=== CATEGORY 1: IDLE STATE (P4) ===\n");
        
        // Test 1: All sensors off
        S_input = 6'b000000;
        check_output(6'b000000, "IDLE - All sensors OFF");
        
        // Test 2: Only S1 active (single sensor, count=1)
        S_input = 6'b000001;
        check_output(6'b000000, "IDLE - Only S1 active (count=1)");
        
        //==========================================================
        // CATEGORY 2: LIGHT DEHYDRATION TESTS (P3 Priority)
        //==========================================================
        $display("\n=== CATEGORY 2: LIGHT DEHYDRATION (P3) ===\n");
        
        // Test 3: S1=1, S2=1 (count=2)
        S_input = 6'b000011;
        check_output(6'b101100, "LIGHT - S1 & S2 active (count=2)");
        
        //==========================================================
        // CATEGORY 3: ACTIVITY ALERT TESTS (P2 Priority)
        //==========================================================
        $display("\n=== CATEGORY 3: ACTIVITY ALERT (P2) ===\n");
        
        // Test 4: Only S6 active
        S_input = 6'b100000;
        check_output(6'b101110, "ACTIVITY - Only S6 active");
        
        //==========================================================
        // CATEGORY 4: SEVERE DEHYDRATION TESTS (P1 Priority)
        //==========================================================
        $display("\n=== CATEGORY 4: SEVERE DEHYDRATION (P1) ===\n");
        
        // Test 5: S5=1, S1=1 (P1 condition)
        S_input = 6'b010001;
        check_output(6'b111111, "SEVERE - S5 & S1 active");
        
        //==========================================================
        // TEST SUMMARY
        //==========================================================
        #100;
        $display("\n");
        $display("***********************************************");
        $display("*            TEST SUMMARY                     *");
        $display("***********************************************");
        $display("Total Tests:  %0d", test_count);
        $display("Passed:       %0d", pass_count);
        $display("Failed:       %0d", fail_count);
        $display("Success Rate: %0d%%", (pass_count * 100) / test_count);
        $display("***********************************************");
        
        if (fail_count == 0) begin
            $display("\n[SUCCESS] All tests passed!");
        end else begin
            $display("\n[WARNING] Some tests failed!");
        end
        
        $display("\n");
        $finish;
    end
    
    //==========================================================
    // CONTINUOUS MONITORING
    //==========================================================
    
    // 1. Logic to update the string name whenever the state changes
    always @(uut.current_state) begin
        case (uut.current_state)
            2'b00: state_name = "IDLE       ";
            2'b01: state_name = "LIGHT      ";
            2'b10: state_name = "SEVERE     ";
            2'b11: state_name = "ACTIVITY   ";
            default: state_name = "UNKNOWN    ";
        endcase
    end

    // 2. The monitor task simply prints the variable
    initial begin
        $display("\n=== CONTINUOUS STATE MONITORING ===");
        $display("Time(ns) | Reset | S_Input  | State | A_Output | State_Name");
        $display("---------|-------|----------|-------|----------|-------------");
        
        $monitor("%7t |    %b    | %b |  %b    | %b | %s", 
                 $time, reset_n, S_input, uut.current_state, A_output, state_name);
    end
    
    //==========================================================
    // TIMEOUT WATCHDOG
    //==========================================================
    initial begin
        #100000;  // 100 microseconds timeout
        $display("\n[ERROR] Simulation timeout!");
        $finish;
    end

endmodule

Verilog/fsm_waveform.vcd
$date
	Sun Dec 07 15:50:36 2025
$end
$version
	Icarus Verilog
$end
$timescale
	1ps
$end
$scope module tb_fsm_wearable $end
$var wire 2 ! state_out [1:0] $end
$var wire 6 " A_output [5:0] $end
$var reg 6 # S_input [5:0] $end
$var reg 1 $ clk $end
$var reg 1 % reset_n $end
$var reg 80 & state_name [80:1] $end
$var integer 32 ' fail_count [31:0] $end
$var integer 32 ( pass_count [31:0] $end
$var integer 32 ) test_count [31:0] $end
$scope module uut $end
$var wire 1 $ clk $end
$var wire 1 * p1_detect $end
$var wire 1 % rst_n $end
$var wire 6 + sensor_inputs [5:0] $end
$var wire 1 , p3_detect $end
$var wire 1 - p2_detect $end
$var wire 3 . active_sensor_count [2:0] $end
$var reg 6 / actuator_outputs [5:0] $end
$var reg 2 0 current_state [1:0] $end
$var reg 2 1 next_state [1:0] $end
$var reg 2 2 state_code [1:0] $end
$var reg 6 3 sync_buffer1 [5:0] $end
$var reg 6 4 sync_buffer2 [5:0] $end
$upscope $end
$scope task apply_reset $end
$upscope $end
$scope task check_output $end
$var reg 6 5 expected [5:0] $end
$var reg 400 6 test_name [400:1] $end
$upscope $end
$upscope $end
$enddefinitions $end
#0
$dumpvars
bx 6
bx 5
b0 4
b0 3
b0 2
b0 1
b0 0
b0 /
b0 .
0-
0,
b0 +
0*
b0 )
b0 (
b0 '
b1000100010011000100010100100000001000000010000000100000001000000010000000100000 &
0%
0$
b0 #
b0 "
b0 !
$end
#5000
1$
#10000
0$
#15000
1$
#20000
0$
#25000
1$
#30000
0$
1%
#35000
1$
#40000
0$
#45000
1$
#50000
0$
b1 )
b1001001010001000100110001000101001000000010110100100000010000010110110001101100001000000111001101100101011011100111001101101111011100100111001100100000010011110100011001000110 6
b0 5
#55000
1$
#60000
0$
#65000
1$
#70000
0$
#75000
1$
#80000
0$
#85000
1$
#90000
0$
#95000
1$
#100000
0$
b10 )
b1001001010001000100110001000101001000000010110100100000010011110110111001101100011110010010000001010011001100010010000001100001011000110111010001101001011101100110010100100000001010000110001101101111011101010110111001110100001111010011000100101001 6
b1 #
b1 +
b1 (
#105000
b1 3
1$
#110000
0$
#115000
b1 .
b1 4
1$
#120000
0$
#125000
1$
#130000
0$
#135000
1$
#140000
0$
#145000
1$
#150000
0$
b11 )
b100110001001001010001110100100001010100001000000010110100100000010100110011000100100000001001100010000001010011001100100010000001100001011000110111010001101001011101100110010100100000001010000110001101101111011101010110111001110100001111010011001000101001 6
b101100 5
b11 #
b11 +
b10 (
#155000
b11 3
1$
#160000
0$
#165000
b1 1
1,
b10 .
b11 4
1$
#170000
0$
#175000
b101100 "
b101100 /
b1 !
b1 2
b1001001010001110100100001010100001000000010000000100000001000000010000000100000 &
b1 0
1$
#180000
0$
#185000
1$
#190000
0$
#195000
1$
#200000
0$
b100 )
b1000001010000110101010001001001010101100100100101010100010110010010000000101101001000000100111101101110011011000111100100100000010100110011011000100000011000010110001101110100011010010111011001100101 6
b101110 5
b100000 #
b100000 +
b11 (
#205000
b100000 3
1$
#210000
0$
#215000
b11 1
1-
0,
b0 .
b100000 4
1$
#220000
0$
#225000
b1000011010101000100100101010110010010010101010001011001001000000010000000100000 &
b101110 "
b101110 /
b11 !
b11 2
b11 0
1$
#230000
0$
#235000
1$
#240000
0$
#245000
1$
#250000
0$
b101 )
b101001101000101010101100100010101010010010001010010000000101101001000000101001100110101001000000010011000100000010100110011000100100000011000010110001101110100011010010111011001100101 6
b111111 5
b10001 #
b10001 +
b100 (
#255000
b10001 3
1$
#260000
0$
#265000
1*
b10 1
0-
1,
b10 .
b10001 4
1$
#270000
0$
#275000
b111111 "
b111111 /
b10 !
b10 2
b1000101010101100100010101010010010001010010000000100000001000000010000000100000 &
b10 0
1$
#280000
0$
#285000
1$
#290000
0$
#295000
1$
#300000
0$
b101 (
